xiaobaiapi/__init__.py
xiaobaiapi/__version__.py
xiaobaiapi/xiaobaiapi.py
xiaobaiapi-0.1.1.dist-info/LICENSE
xiaobaiapi-0.1.1.dist-info/METADATA
xiaobaiapi-0.1.1.dist-info/WHEEL
xiaobaiapi-0.1.1.dist-info/top_level.txt
xiaobaiapi-0.1.1.dist-info/RECORD
