Metadata-Version: 2.1
Name: xiaobaiapi
Version: 0.1.1
Summary: xiaobaiapi 让接口测试起来更简单、人性化、更好玩  公众号：小白科技之窗
Home-page: https://gitee.com/xiaobaikeji/xiaobaiapi
Author: Tser
Author-email: 807447312@qq.com
License: UNKNOWN
Keywords: test api autoapi xiaobai xiaobaiapi httpclient
Platform: UNKNOWN
Classifier: Programming Language :: Python :: 3.6
Classifier: Programming Language :: Python :: 3.7
Classifier: Programming Language :: Python :: 3.8
Classifier: Programming Language :: Python :: 3.9
Classifier: Programming Language :: Python :: 3.10
Classifier: License :: OSI Approved :: Apache Software License
Classifier: Operating System :: OS Independent
Requires-Python: >=3.6
License-File: LICENSE
Requires-Dist: lxml
Requires-Dist: jmespath
Requires-Dist: requests
